daumdict/__init__.py
daumdict/__main__.py
daumdict/exceptions.py
daumdict/get_translation.py
daumdict-0.2.dist-info/METADATA
daumdict-0.2.dist-info/WHEEL
daumdict-0.2.dist-info/top_level.txt
daumdict-0.2.dist-info/RECORD
