Metadata-Version: 2.1
Name: daumdict
Version: 0.2
Summary: find a word from daum dict.
Home-page: https://github.com/love-adela/daumdict
Author: love-adela
Author-email: love.adelar@gmail.com
License: MIT
Classifier: Programming Language :: Python :: 3
Classifier: License :: OSI Approved :: MIT License
Classifier: Operating System :: OS Independent
Requires-Python: >=3.8
Requires-Dist: requests
Requires-Dist: BeautifulSoup4
